basinentropy/__init__.py
basinentropy/basin_entropy.py
basinentropycalc-0.1.7.dist-info/LICENSE
basinentropycalc-0.1.7.dist-info/METADATA
basinentropycalc-0.1.7.dist-info/WHEEL
basinentropycalc-0.1.7.dist-info/top_level.txt
basinentropycalc-0.1.7.dist-info/RECORD
