Metadata-Version: 2.1
Name: basinentropycalc
Version: 0.1.7
Summary: This script computes the basin entropy of a computed basin of attraction on a regular grid.The function return the basin entropy and the boundary basin entropy
Home-page: https://github.com/jonasferoliveira/basin_entropy
Author: Oliveira, Jonas
Author-email: jonasferoliveira.ufg@gmail.com
Project-URL: Bug Tracker, https://github.com/jonasferoliveira/basin_entropy/issues
Classifier: Programming Language :: Python :: 3
Classifier: License :: OSI Approved :: MIT License
Classifier: Operating System :: OS Independent
Requires-Python: >=3.6
License-File: LICENSE
